odoo/addons/ssi_appointment_project/README.rst
odoo/addons/ssi_appointment_project/__init__.py
odoo/addons/ssi_appointment_project/__manifest__.py
odoo/addons/ssi_appointment_project/models/__init__.py
odoo/addons/ssi_appointment_project/models/appointment_schedule.py
odoo/addons/ssi_appointment_project/models/appointment_type.py
odoo/addons/ssi_appointment_project/static/description/icon.png
odoo/addons/ssi_appointment_project/views/appointment_schedule_views.xml
odoo/addons/ssi_appointment_project/views/appointment_type_views.xml
odoo14_addon_ssi_appointment_project-14.0.1.6.0.dist-info/METADATA
odoo14_addon_ssi_appointment_project-14.0.1.6.0.dist-info/WHEEL
odoo14_addon_ssi_appointment_project-14.0.1.6.0.dist-info/top_level.txt
odoo14_addon_ssi_appointment_project-14.0.1.6.0.dist-info/RECORD
